Workbook
Name Años: [1]Variables!$A$1:$A$5

Sheet Analisis de Costos
A1: C-172 N
A2: CC-AQI
A4: Variables | B4: USD | C4: 975 | D4: pesos | F4: Consumos | H4: GAL / hr. | I4: Litros / hr.
B5: UF | C5: 39700 | D5: pesos | G5: Combustible | H5: 7 | I5: =H5*3.785 -> 26.495
B6: CLP Litro Avgas | C6: =1750+(0*(1+0.035)^((H11*1.27)/C13)) -> 1750 | D6: pesos | G6: Aceite | H6: =((10*0.95)/3.785)/200 -> 0.012549538 | I6: =H6*3.785 -> 0.0475 | J6: Año | K6: Total | L6: Prom. Mensual
B7: CLP Litro Aceite | C7: =[1]Cuenta!E1739/6 -> 14280 | D7: pesos | J7: 2018 | K7: =SUMIF([1]Libro!U:U,'Analisis de Costos'!J7,[1]Libro!J:J) -> 416.9 | L7: =K7/12 -> 34.741667
B8: TOA | C8: =205000+(0*(1+0.033)^((H11*1.27)/C13)) -> 205000 | D8: pesos | F8: Mantto | H8: Ciclo Hrs. | I8: CLP / Hr. | J8: 2019 | K8: =SUMIF([1]Libro!U:U,'Analisis de Costos'!J8,[1]Libro!J:J) -> 509.5 | L8: =K8/12 -> 42.458333
B9: Seguro USD | C9: =((5700.87*1.19)+(0*(1+0.023)^((H11*1.27)/C13)))*0+(4710.02) -> 4710.02 | D9: dólares | G9: 100 hrs | H9: 100 | I9: =C11/(100*1.27) -> 28172.677 | J9: 2020 | K9: =SUMIF([1]Libro!U:U,'Analisis de Costos'!J9,[1]Libro!J:J) -> 150.8 | L9: =K9/12 -> 12.566667
B10: Cambio Aceite | C10: =281090+(0*(1+0.033)^((H11*1.27)/C13)) -> 281090 | D10: pesos | G10: Cambio aceite | H10: 100 | I10: =C10/(100*1.27) -> 2213.3071 | J10: 2021 | K10: =SUMIF([1]Libro!U:U,'Analisis de Costos'!J10,[1]Libro!J:J) -> 245.8 | L10: =K10/12 -> 20.483333
B11: Revisión 100 hrs | C11: =[1]Cuenta!E1767 -> 3577930 | D11: pesos | G11: Overhaul | H11: =(2000-C14) -> 1379.1 | I11: =C12/((H11+C14)*1.27) -> 31024.286 | J11: 2022 | K11: =SUMIF([1]Libro!U:U,'Analisis de Costos'!J11,[1]Libro!J:J) -> 199 | L11: =K11/12 -> 16.583333
B12: Overhaul | C12: =((46124.63*C4)+(8000000))*(1+0.035)^((2000*1.27/C13)) -> 78801687 | D12: pesos | J12: 2023 | K12: =SUMIF([1]Libro!U:U,'Analisis de Costos'!J12,[1]Libro!J:J) -> 197.9 | L12: =K12/12 -> 16.491667
B13: Horas Anuales | C13: 220 | D13: horas | J13: 2024 | K13: =SUMIF([1]Libro!U:U,'Analisis de Costos'!J13,[1]Libro!J:J) -> 234.96667 | L13: =K13/12 -> 19.580556
B14: Tacómetro Actual | C14: 620.9
B15: Años Remanentes | C15: =((H11*1.27)/C13) -> 7.9611682
A17: Costos | B17: Fijos | D17: Año | F17: Mes | G17: Hora
C18: Seguro | D18: =($C$4*C9) -> 4592269.5 | F18: =D18/12 -> 382689.12 | G18: =D18/C13 -> 20873.952
C19: Hangar | D19: 4963032 | F19: =(D19/12) -> 413586 | G19: =F19/(C13/12) -> 22559.236
C20: TOA + Patentes | D20: =$C$8+(200000+(0*(1+0.033)^((H11*1.27)/C13))) -> 405000 | F20: =D20/12 -> 33750 | G20: =D20/(C13) -> 1840.9091
C21: Contingencias | D21: =2000000+(0*(1+0.033)^8.2) -> 2000000 | F21: =D21/12 -> 166666.67 | G21: =D21/(C13) -> 9090.9091
C22: Impuesto Lujo + Contador | D22: =2200000+(((42644*12)+500000)+((SUM('[1]SII F29 y Contador'!J25:J36))*(1+0.02)^(C15))*0) -> 3211728 | F22: =D22/12 -> 267644 | G22: =D22/($C$13) -> 14598.764
C23: Limpieza | D23: 180000 | F23: =D23/12 -> 15000 | G23: =D23/C13 -> 818.18182
C24: Overhaul | D24: =(C12-C40)/C15 -> 8010173.5 | F24: =D24/12 -> 667514.46 | G24: =F24/(C13/12) -> 36409.879
C25: Total | D25: =SUM(D18:D24) -> 23362203 | F25: =SUM(F18:F24) -> 1946850.2 | G25: =SUM(G18:G24) -> 106191.83
C26: Total Fijo/ hora | G26: =SUM(G18:G24) -> 106191.83
B28: Variables | D28: CLP / Hr.
C29: Combustible | D29: =I5*C6 -> 46366.25
C30: Aceite | D30: =I6*C7 -> 678.3
C31: Mantto | D31: =I9+I10 -> 30385.984
C32: Total Variable/ hora | D32: =SUM(D29:D31) -> 77430.534
A35: Total costo hora | C35: =G26+D32 -> 183622.37
A38: Cash Overhaul | C38: =(((G24))*(C14*1.27)) -> 28710756
A39: Credito Overhaul | C39: =C12-C38 -> 50090932
A40: Recaudado | C40: =(11000000)*(1+0.04)^C15 -> 15031349
A41: Valor Hora | C41: =SUM([1]Libro!AF:AF) -> 168052.2
A42: Ganancia/ Hora | C42: =-1*(C35-C41) -> -15570.169
A43: Falta | C43: =C38-C40 -> 13679406
A44: Años remanente Overhaul | C44: =(H11*1.27)/C13 -> 7.9611682
A45: Meta | C45: =C12-C40 -> 63770338
